{
  "version": "1.0.0",
  "lastScanned": 1776314304335,
  "projectRoot": "C:\\Users\\wogus\\Desktop\\03. Project\\01. Playground\\new_procpa_blog",
  "techStack": {
    "languages": [
      {
        "name": "JavaScript/TypeScript",
        "version": null,
        "confidence": "high",
        "markers": [
          "package.json"
        ]
      },
      {
        "name": "TypeScript",
        "version": null,
        "confidence": "high",
        "markers": [
          "tsconfig.json"
        ]
      }
    ],
    "frameworks": [
      {
        "name": "next",
        "version": "16.2.2",
        "category": "fullstack"
      },
      {
        "name": "react",
        "version": "19.2.4",
        "category": "frontend"
      },
      {
        "name": "react-dom",
        "version": "19.2.4",
        "category": "frontend"
      }
    ],
    "packageManager": "npm",
    "runtime": null
  },
  "build": {
    "buildCommand": "npm run build",
    "testCommand": null,
    "lintCommand": "npm run lint",
    "devCommand": "npm run dev",
    "scripts": {
      "predev": "velite",
      "dev": "next dev",
      "prebuild": "velite",
      "build": "next build",
      "start": "next start",
      "lint": "eslint",
      "content": "velite",
      "content:watch": "velite --watch"
    }
  },
  "conventions": {
    "namingStyle": null,
    "importStyle": null,
    "testPattern": null,
    "fileOrganization": "type-based"
  },
  "structure": {
    "isMonorepo": false,
    "workspaces": [],
    "mainDirectories": [
      "public",
      "src"
    ],
    "gitBranches": {
      "defaultBranch": "master",
      "branchingStrategy": null
    }
  },
  "customNotes": [],
  "directoryMap": {
    "content": {
      "path": "content",
      "purpose": null,
      "fileCount": 0,
      "lastAccessed": 1776314304223,
      "keyFiles": []
    },
    "public": {
      "path": "public",
      "purpose": "Public files",
      "fileCount": 17,
      "lastAccessed": 1776314304224,
      "keyFiles": [
        "apple-touch-icon.png",
        "favicon.ico",
        "file.svg",
        "globe.svg",
        "manifest.json"
      ]
    },
    "src": {
      "path": "src",
      "purpose": "Source code",
      "fileCount": 0,
      "lastAccessed": 1776314304257,
      "keyFiles": []
    },
    "src\\app": {
      "path": "src\\app",
      "purpose": "Application code",
      "fileCount": 8,
      "lastAccessed": 1776314304259,
      "keyFiles": [
        "apple-touch-icon.png",
        "favicon.ico",
        "globals.css"
      ]
    },
    "src\\components": {
      "path": "src\\components",
      "purpose": "UI components",
      "fileCount": 20,
      "lastAccessed": 1776314304260,
      "keyFiles": [
        "backlinks-panel.tsx",
        "command-palette.tsx",
        "content-aside.tsx"
      ]
    },
    "src\\lib": {
      "path": "src\\lib",
      "purpose": "Library code",
      "fileCount": 6,
      "lastAccessed": 1776314304260,
      "keyFiles": [
        "about-data.ts",
        "search.ts",
        "theme-script.ts"
      ]
    }
  },
  "hotPaths": [],
  "userDirectives": []
}